Workbook

Sheet 汇总
A1: 本地库字段命名风格统计（schema = as_agent）
A2: 口径：实查 information_schema.columns；「下划线列」= 列名含 _ ；「多词连写列」= 列名不含 _ 且长度 ≥ 9（原驼峰被 openGauss 折叠为全小写）。所有指标均由「表清单」sheet 实时汇总。
A3: 命名风格 | B3: 表数量 | C3: 其中备份表 | D3: 业务表数量 | E3: 总列数 | F3: 下划线列 | G3: 多词连写列 | H3: 说明
A4: A 纯下划线 | B4: =COUNTIF(表清单!$C$2:$C$294,$A4) -> 53 | C4: =COUNTIFS(表清单!$C$2:$C$294,$A4,表清单!$D$2:$D$294,"备份表") -> 3 | D4: =B4-C4 -> 50 | E4: =SUMIF(表清单!$C$2:$C$294,$A4,表清单!$E$2:$E$294) -> 582 | F4: =SUMIF(表清单!$C$2:$C$294,$A4,表清单!$F$2:$F$294) -> 488 | G4: =SUMIF(表清单!$C$2:$C$294,$A4,表清单!$G$2:$G$294) -> 0 | H4: 多词字段一律下划线分隔，符合主流规范
A5: B 混用 | B5: =COUNTIF(表清单!$C$2:$C$294,$A5) -> 46 | C5: =COUNTIFS(表清单!$C$2:$C$294,$A5,表清单!$D$2:$D$294,"备份表") -> 18 | D5: =B5-C5 -> 28 | E5: =SUMIF(表清单!$C$2:$C$294,$A5,表清单!$E$2:$E$294) -> 922 | F5: =SUMIF(表清单!$C$2:$C$294,$A5,表清单!$F$2:$F$294) -> 427 | G5: =SUMIF(表清单!$C$2:$C$294,$A5,表清单!$G$2:$G$294) -> 274 | H5: 既有下划线列、又有多词连写列，多为多次改表遗留
A6: C 全连写 | B6: =COUNTIF(表清单!$C$2:$C$294,$A6) -> 194 | C6: =COUNTIFS(表清单!$C$2:$C$294,$A6,表清单!$D$2:$D$294,"备份表") -> 104 | D6: =B6-C6 -> 90 | E6: =SUMIF(表清单!$C$2:$C$294,$A6,表清单!$E$2:$E$294) -> 3737 | F6: =SUMIF(表清单!$C$2:$C$294,$A6,表清单!$F$2:$F$294) -> 0 | G6: =SUMIF(表清单!$C$2:$C$294,$A6,表清单!$G$2:$G$294) -> 2816 | H6: 原驼峰被折叠成全小写连写（如 reportno），无下划线列
A7: 合计 | B7: =SUM(B4:B6) -> 293 | C7: =SUM(C4:C6) -> 125 | D7: =SUM(D4:D6) -> 168 | E7: =SUM(E4:E6) -> 5241 | F7: =SUM(F4:F6) -> 915 | G7: =SUM(G4:G6) -> 3090 | H7: 293 张表、5241 列（含 125 张 bak 备份表）
A9: 关键结论：
A10: 1. 全库不存在「真·驼峰（列名含大写字母）」的业务表。openGauss 会把未加双引号的标识符折叠为小写，所以驼峰写法落库后一律变成全小写连写（reportno / customername / checktaskno）。
A11: 2. 唯一保留大写字母的列只有 CONDITION，出现在 app_credit_approval_manage_req_info 及其 3 张 bak 表。它是保留字，建表时加了双引号；查/写 SQL 必须写成 "CONDITION"，否则报 column "condition" does not exist。
A12: 3. 纯下划线风格的 53 张表集中在中后台配置类：sys_*、knowledge_*、ext_intf_*、collector_*、rule_*、prompt_* 等。
A13: 4. 全连写 194 张表中有 104 张是 bak_ 备份表；真正的业务表（app_* / xd_* / ws_* / zx_* / dfs_*）基本都走连写风格。
A14: 5. 混用的 46 张表风险最高：同一张表里两套写法并存（如 index_params 有 count_field 也有 publicparamstatus），写 SQL 与做实体映射时最容易踩坑。

Sheet 表清单
A1: 序号 | B1: 表名 | C1: 命名风格 | D1: 表类别 | E1: 总列数 | F1: 下划线列数 | G1: 多词连写列数 | H1: 含大写列数 | I1: 下划线列清单 | J1: 备注
A2: 1 | B2: agent_config | C2: A 纯下划线 | D2: 业务表 | E2: 14 | F2: 13 | G2: 0 | H2: 0 | I2: agent_name,agent_code,entity_type,agent_topic,agent_addr,agent_detail,agent_prompt,has_statistics,agent_status,input_time,update_time,agent_param_tpl,large_model_code
A3: 2 | B3: agent_rule | C3: A 纯下划线 | D3: 业务表 | E3: 21 | F3: 18 | G3: 0 | H3: 0 | I3: rule_name,rule_text,parsed_expression,rule_status,input_time,input_user,update_time,update_user,prompt_key,threshold_config,risk_remark,disposal_advice,additional_analysis,rule_code,additional_analysis_name,rule_struct,fact_analysis,request_params
A4: 3 | B4: app_code_dict | C4: A 纯下划线 | D4: 业务表 | E4: 5 | F4: 3 | G4: 0 | H4: 0 | I4: dict_type,code_value,code_name
A5: 4 | B5: bak_20260916_agent_rule | C5: A 纯下划线 | D5: 备份表 | E5: 2 | F5: 1 | G5: 0 | H5: 0 | I5: request_params | J5: bak 备份表
A6: 5 | B6: bak_20260916_kb_params | C6: A 纯下划线 | D6: 备份表 | E6: 3 | F6: 2 | G6: 0 | H6: 0 | I6: relate_index_set,input_param | J6: bak 备份表
A7: 6 | B7: bak_20260916_relate_input_param | C7: A 纯下划线 | D7: 备份表 | E7: 2 | F7: 1 | G7: 0 | H7: 0 | I7: input_param | J7: bak 备份表
A8: 7 | B8: call_llm_record | C8: A 纯下划线 | D8: 业务表 | E8: 13 | F8: 11 | G8: 0 | H8: 0 | I8: hub_account,trace_id,sort_no,request_time,request_body,response_time,large_model_code,api_key,prompt_tokens,completion_tokens,session_msg_no
A9: 8 | B9: collector_config | C9: A 纯下划线 | D9: 业务表 | E9: 8 | F9: 6 | G9: 0 | H9: 0 | I9: config_name,collector_type,config_json,cron_expression,created_at,updated_at
A10: 9 | B10: collector_config_1 | C10: A 纯下划线 | D10: 业务表 | E10: 8 | F10: 6 | G10: 0 | H10: 0 | I10: config_name,collector_type,config_json,cron_expression,created_at,updated_at
A11: 10 | B11: collector_config_2 | C11: A 纯下划线 | D11: 业务表 | E11: 6 | F11: 4 | G11: 0 | H11: 0 | I11: config_name,collector_type,config_json,cron_expression
A12: 11 | B12: credit_record | C12: A 纯下划线 | D12: 业务表 | E12: 12 | F12: 10 | G12: 0 | H12: 0 | I12: customer_id,contract_no,loan_type,loan_amount,loan_balance,start_date,end_date,loan_purpose,guarantee_type,created_at
A13: 12 | B13: ext_intf_manage | C13: A 纯下划线 | D13: 业务表 | E13: 23 | F13: 22 | G13: 0 | H13: 0 | I13: supplier_id,intf_no,intf_name,intf_path,intf_type_name,intf_request_type,intf_time_out,intf_status,intf_desc,refer_intf_no,refer_intf_status,async_save,battle_flag,battle_report_content,before_handler,input_user_id,input_user_name,input_time,update_user_id,update_user_name,update_time,intf_structure
A14: 13 | B14: ext_intf_param_define | C14: A 纯下划线 | D14: 业务表 | E14: 13 | F14: 12 | G14: 0 | H14: 0 | I14: supplier_id,param_code,param_type,param_value,input_user_id,input_user_name,input_time,update_user_id,update_user_name,update_time,param_position,param_is_required
A15: 14 | B15: ext_intf_param_manage | C15: A 纯下划线 | D15: 业务表 | E15: 25 | F15: 24 | G15: 0 | H15: 0 | I15: supplier_id,intf_no,param_code,param_name,param_type,param_is_required,param_position,param_source,param_value,input_user_id,input_user_name,input_time,update_user_id,update_user_name,update_time,source_type_detail,source_param_code,source_param_type,child_param_code,child_param_name,child_param_type,source_field_dict_id,source_field,source_field_name
A16: 15 | B16: ext_intf_supplier_manage | C16: A 纯下划线 | D16: 业务表 | E16: 11 | F16: 10 | G16: 0 | H16: 0 | I16: supplier_id,supplier_name,intf_type,intf_path,input_user_id,input_user_name,input_time,update_user_id,update_user_name,update_time
A17: 16 | B17: index_relate_index_info | C17: A 纯下划线 | D17: 业务表 | E17: 8 | F17: 7 | G17: 0 | H17: 0 | I17: param_no,relate_param_no,relate_param_id,relate_param_name,relate_group_id,create_time,update_time
A18: 17 | B18: index_relate_info | C18: A 纯下划线 | D18: 业务表 | E18: 5 | F18: 3 | G18: 0 | H18: 0 | I18: index_id,relate_index_id,relate_time
A19: 18 | B19: index_relate_knowledge_info | C19: A 纯下划线 | D19: 业务表 | E19: 9 | F19: 8 | G19: 0 | H19: 0 | I19: param_no,relate_knowledge_no,relate_knowledge_code,relate_knowledge_name,relate_group_id,relate_items,create_time,update_time
... A56: 55 | B56: app_shareholder_info | C56: B 混用 | D56: 业务表 | E56: 13 | F56: 6 | G56: 3 | H56: 0 | I56: stock_num,stock_percent,is_quoted,is_state_owned,is_fake_state_owned,is_listed_company
A57: 56 | B57: bak_20260922_app_ic_shareholder_info | C57: B 混用 | D57: 备份表 | E57: 13 | F57: 1 | G57: 9 | H57: 0 | I57: snapshot_type | J57: bak 备份表
A58: 57 | B58: bak_20260922_app_shareholder_info | C58: B 混用 | D58: 备份表 | E58: 13 | F58: 6 | G58: 3 | H58: 0 | I58: stock_num,stock_percent,is_quoted,is_state_owned,is_fake_state_owned,is_listed_company | J58: bak 备份表
A59: 58 | B59: bak_20260922_dfs_crdt_loan_cust_rel | C59: B 混用 | D59: 备份表 | E59: 42 | F59: 34 | G59: 3 | H59: 0 | I59: cr_cust_num,cust_nm,stat_cur,tax_sale_amt_tot,tax_sale_amt_ch,tax_sale_amt_tb,mon_sale_amt,fin_rpt_dt,fin_rpt_clber,rcvb_fnd_on_acct,oprt_incm,due_fnd_on_acct,acct_zhxx,fzn_amt,dep_y_avg_bal,yr_pty_income,yr_pty_income_ch,yr_pty_income_regy,elec_income,elec_income_ch,elec_income_regy,cr_acr_amt_1,cr_acr_amt_2,dbt_cntpr_and_acr_amt,cr_cntpr_and_acr_amt,hnym_tfrd_amt_dbt_pcnt,hnym_tfrd_amt_cr_pcnt,instd_sal_moly,instd_sal_person_moly,instd_sal_amt_moly,instd_sal_person_moly_hb,instd_sal_amt_moly_hb,instd_sal_person_moly_tb,instd_sal_amt_moly_tb | J59: bak 备份表
A60: 59 | B60: bak_20260922_dfs_final_crdt_loan_cust_rel | C60: B 混用 | D60: 备份表 | E60: 16 | F60: 7 | G60: 5 | H60: 0 | I60: cr_cust_num,cust_nm,rsk_ev,spf_intra,business_time,prmpt_ltr,ev_tp | J60: bak 备份表
A61: 60 | B61: bak_20260922_gfzx_balance_sheet_item | C61: B 混用 | D61: 备份表 | E61: 11 | F61: 5 | G61: 3 | H61: 0 | I61: c_cn_name,c_before_last_qmye,c_last_qmye,c_last_time_qmye,c_current_qmye | J61: bak 备份表
A62: 61 | B62: bak_20260922_gfzx_finance_index_item | C62: B 混用 | D62: 备份表 | E62: 11 | F62: 5 | G62: 3 | H62: 0 | I62: o_cn_name,o_before_last_index,o_last_index,o_last_time_index,o_current_index | J62: bak 备份表
A63: 62 | B63: bak_20260922_gfzx_national_dev | C63: B 混用 | D63: 备份表 | E63: 17 | F63: 12 | G63: 3 | H63: 0 | I63: c_beforeyear,c_lastyear,c_correspondingperiodlastyear,c_sameperiodthisyear,n_beforeyear,n_lastyear,n_correspondingperiodlastyear,n_sameperiodthisyear,o_beforeyear,o_lastyear,o_correspondingperiodlastyear,o_sameperiodthisyear | J63: bak 备份表
A64: 63 | B64: bak_20260922_gfzx_profit_sheet_item | C64: B 混用 | D64: 备份表 | E64: 11 | F64: 5 | G64: 3 | H64: 0 | I64: n_cn_name,n_before_last_qmye,n_last_qmye,n_last_time_qmye,n_current_qmye | J64: bak 备份表
A65: 64 | B65: bak_20260922_std_ecis_t_mining_tags_dd | C65: B 混用 | D65: 备份表 | E65: 9 | F65: 4 | G65: 3 | H65: 0 | I65: cr_cust_num,entp_first_nm,tag_id,tag_name | J65: bak 备份表
A66: 65 | B66: bak_20260922_ws_base_info | C66: B 混用 | D66: 备份表 | E66: 32 | F66: 20 | G66: 3 | H66: 0 | I66: actual_capi,org_no,term_end,credit_no,start_date,district_code,quoted_type,regist_capi,reg_no,belong_org,oper_name,econ_kind_code,end_date,econ_kind,new_status,is_quoted,term_start,collegues_num,is_history,check_date | J66: bak 备份表
A67: 66 | B67: bak_20260922_ws_beneficial_owner | C67: B 混用 | D67: 备份表 | E67: 12 | F67: 1 | G67: 5 | H67: 0 | I67: law_desc | J67: bak 备份表
A68: 67 | B68: bak_20260922_ws_best_shareholding | C68: B 混用 | D68: 备份表 | E68: 17 | F68: 8 | G68: 3 | H68: 0 | I68: sh_type,credit_no,subscribed_amount,stock_num,real_capi,con_date,currency_code,real_capi_date | J68: bak 备份表
... A74: 73 | B74: bak_20260922y_ws_equity_change | C74: B 混用 | D74: 备份表 | E74: 11 | F74: 4 | G74: 3 | H74: 0 | I74: before_percent,change_date,after_percent,public_date | J74: bak 备份表
A75: 74 | B75: customer | C75: B 混用 | D75: 业务表 | E75: 22 | F75: 18 | G75: 1 | H75: 0 | I75: company_name,credit_code,legal_person,actual_controller,registered_capital,paid_capital,establish_date,biz_scope,register_address,holding_type,group_name,customer_type,first_loan_date,last_approval_date,main_bank,settlement_bank,created_at,updated_at
A76: 75 | B76: dfs_crdt_loan_cust_rel | C76: B 混用 | D76: 业务表 | E76: 42 | F76: 34 | G76: 3 | H76: 0 | I76: cr_cust_num,cust_nm,stat_cur,tax_sale_amt_tot,tax_sale_amt_ch,tax_sale_amt_tb,mon_sale_amt,fin_rpt_dt,fin_rpt_clber,rcvb_fnd_on_acct,oprt_incm,due_fnd_on_acct,acct_zhxx,fzn_amt,dep_y_avg_bal,yr_pty_income,yr_pty_income_ch,yr_pty_income_regy,elec_income,elec_income_ch,elec_income_regy,cr_acr_amt_1,cr_acr_amt_2,dbt_cntpr_and_acr_amt,cr_cntpr_and_acr_amt,hnym_tfrd_amt_dbt_pcnt,hnym_tfrd_amt_cr_pcnt,instd_sal_moly,instd_sal_person_moly,instd_sal_amt_moly,instd_sal_person_moly_hb,instd_sal_amt_moly_hb,instd_sal_person_moly_tb,instd_sal_amt_moly_tb
A77: 76 | B77: dfs_final_crdt_loan_cust_rel | C77: B 混用 | D77: 业务表 | E77: 16 | F77: 7 | G77: 5 | H77: 0 | I77: cr_cust_num,cust_nm,rsk_ev,spf_intra,business_time,prmpt_ltr,ev_tp
A78: 77 | B78: gfzx_balance_sheet_item | C78: B 混用 | D78: 业务表 | E78: 11 | F78: 5 | G78: 3 | H78: 0 | I78: c_cn_name,c_before_last_qmye,c_last_qmye,c_last_time_qmye,c_current_qmye
A79: 78 | B79: gfzx_finance_index_item | C79: B 混用 | D79: 业务表 | E79: 11 | F79: 5 | G79: 3 | H79: 0 | I79: o_cn_name,o_before_last_index,o_last_index,o_last_time_index,o_current_index
A80: 79 | B80: gfzx_national_dev | C80: B 混用 | D80: 业务表 | E80: 17 | F80: 12 | G80: 3 | H80: 0 | I80: c_beforeyear,c_lastyear,c_correspondingperiodlastyear,c_sameperiodthisyear,n_beforeyear,n_lastyear,n_correspondingperiodlastyear,n_sameperiodthisyear,o_beforeyear,o_lastyear,o_correspondingperiodlastyear,o_sameperiodthisyear
A81: 80 | B81: gfzx_profit_sheet_item | C81: B 混用 | D81: 业务表 | E81: 11 | F81: 5 | G81: 3 | H81: 0 | I81: n_cn_name,n_before_last_qmye,n_last_qmye,n_last_time_qmye,n_current_qmye
A82: 81 | B82: index_params | C82: B 混用 | D82: 业务表 | E82: 59 | F82: 7 | G82: 41 | H82: 0 | I82: count_field,is_online,metric_intro,data_unit,data_example,data_type,data_content_parse
A83: 82 | B83: index_params_version | C83: B 混用 | D83: 业务表 | E83: 54 | F83: 1 | G83: 42 | H83: 0 | I83: count_field
A84: 83 | B84: knowledge_base_params | C84: B 混用 | D84: 业务表 | E84: 46 | F84: 23 | G84: 15 | H84: 0 | I84: input_param,large_model_code,trace_config,image_config,whole_source_config,large_model_content,relate_index_set,black_content_desc,black_model_code,is_markdown,param_description,input_condition,is_client_search,is_online_search,input_index,large_model_param,is_top,splitter_param,tool_parameters_config,is_cloud_search,user_prompt,split_strategy_param,business_experience
A85: 84 | B85: knowledge_rule | C85: B 混用 | D85: 业务表 | E85: 9 | F85: 6 | G85: 1 | H85: 0 | I85: rule_code,rule_name,rule_type,created_at,updated_at,sort_order
A86: 85 | B86: rule_condition | C86: B 混用 | D86: 业务表 | E86: 7 | F86: 4 | G86: 1 | H86: 0 | I86: rule_id,indicator_key,logic_order,logic_connector
... A100: 99 | B100: zx_per_credit_info | C100: B 混用 | D100: 业务表 | E100: 48 | F100: 35 | G100: 9 | H100: 0 | I100: zx_record_no,grzx_234,total_count,jy_loan_bal,xf_loan_bal,zf_loan_bal,qt_loan_bal,total_bal,jy_loan_count,xf_loan_count,zf_loan_count,qt_loan_count,bzc_bal,bad_bal,loan_current_total_overdue,credit_card_cur_total_overdue,gr_dwdb_ovd_amt,as_all_all_class2_balamt,gr_as_defaultclass_balamt,gr_dwdb_wjfl_abn_bal,spec_ext_balance,spec_delay_balance,gr_wjq_crd_wjfl_abn_bal,gr_wjq_acct_st_abn_bal,gr_wxh_cc_st_abn_bal,gr_dwdb_hk_st_abn_bal,gr_fyjg_liab_tot,gr_fyjg_dwdb_bal,query_02_12,query_02_6,query_02_3,query_03_12,query_03_6,query_03_3,gr_fyjg_gjlv_loan_max
A101: 100 | B101: agent_rule_prompt | C101: C 全连写 | D101: 业务表 | E101: 2 | F101: 0 | G101: 0 | H101: 0
A102: 101 | B102: app_capital_flow_info | C102: C 全连写 | D102: 业务表 | E102: 15 | F102: 0 | G102: 12 | H102: 0
A103: 102 | B103: app_check_index_info | C103: C 全连写 | D103: 业务表 | E103: 11 | F103: 0 | G103: 7 | H103: 0
A104: 103 | B104: app_check_object_info | C104: C 全连写 | D104: 业务表 | E104: 14 | F104: 0 | G104: 11 | H104: 0
A105: 104 | B105: app_check_opinion_info | C105: C 全连写 | D105: 业务表 | E105: 10 | F105: 0 | G105: 8 | H105: 0
A106: 105 | B106: app_check_record_info | C106: C 全连写 | D106: 业务表 | E106: 9 | F106: 0 | G106: 6 | H106: 0
A107: 106 | B107: app_collateral_info | C107: C 全连写 | D107: 业务表 | E107: 20 | F107: 0 | G107: 9 | H107: 0
A108: 107 | B108: app_collateral_mortgage_info | C108: C 全连写 | D108: 业务表 | E108: 14 | F108: 0 | G108: 9 | H108: 0
A109: 108 | B109: app_collateral_restricted_right | C109: C 全连写 | D109: 业务表 | E109: 8 | F109: 0 | G109: 5 | H109: 0
A110: 109 | B110: app_credit_approval_manage_req_info | C110: C 全连写 | D110: 业务表 | E110: 9 | F110: 0 | G110: 6 | H110: 1 | J110: 含大写列，SQL 中须加双引号
A111: 110 | B111: app_credit_debt_detail | C111: C 全连写 | D111: 业务表 | E111: 13 | F111: 0 | G111: 8 | H111: 0
A112: 111 | B112: app_credit_query_info | C112: C 全连写 | D112: 业务表 | E112: 16 | F112: 0 | G112: 14 | H112: 0
A113: 112 | B113: app_credit_report_info | C113: C 全连写 | D113: 业务表 | E113: 52 | F113: 0 | G113: 50 | H113: 0
A114: 113 | B114: app_credit_use_info | C114: C 全连写 | D114: 业务表 | E114: 17 | F114: 0 | G114: 13 | H114: 0
A115: 114 | B115: app_customer_info | C115: C 全连写 | D115: 业务表 | E115: 19 | F115: 0 | G115: 16 | H115: 0
A116: 115 | B116: app_early_warning_info | C116: C 全连写 | D116: 业务表 | E116: 15 | F116: 0 | G116: 10 | H116: 0
A117: 116 | B117: app_early_warning_opinion_info | C117: C 全连写 | D117: 业务表 | E117: 14 | F117: 0 | G117: 9 | H117: 0
A118: 117 | B118: app_early_warning_signal_info | C118: C 全连写 | D118: 业务表 | E118: 12 | F118: 0 | G118: 7 | H118: 0
A119: 118 | B119: app_entrust_pay_info | C119: C 全连写 | D119: 业务表 | E119: 9 | F119: 0 | G119: 6 | H119: 0
A120: 119 | B120: app_finance_index_info | C120: C 全连写 | D120: 业务表 | E120: 16 | F120: 0 | G120: 12 | H120: 0
A121: 120 | B121: app_finance_indicator_info | C121: C 全连写 | D121: 业务表 | E121: 57 | F121: 0 | G121: 50 | H121: 0
A122: 121 | B122: app_finance_report_info | C122: C 全连写 | D122: 业务表 | E122: 14 | F122: 0 | G122: 10 | H122: 0
... A154: 153 | B154: app_xd_shareholder_info | C154: C 全连写 | D154: 业务表 | E154: 14 | F154: 0 | G154: 10 | H154: 0
A155: 154 | B155: bak_20260916_index_params | C155: C 全连写 | D155: 备份表 | E155: 2 | F155: 0 | G155: 0 | H155: 0 | J155: bak 备份表
A156: 155 | B156: bak_20260922_app_capital_flow_info | C156: C 全连写 | D156: 备份表 | E156: 15 | F156: 0 | G156: 12 | H156: 0 | J156: bak 备份表
A157: 156 | B157: bak_20260922_app_check_index_info | C157: C 全连写 | D157: 备份表 | E157: 11 | F157: 0 | G157: 7 | H157: 0 | J157: bak 备份表
A158: 157 | B158: bak_20260922_app_check_object_info | C158: C 全连写 | D158: 备份表 | E158: 13 | F158: 0 | G158: 10 | H158: 0 | J158: bak 备份表
A159: 158 | B159: bak_20260922_app_check_opinion_info | C159: C 全连写 | D159: 备份表 | E159: 10 | F159: 0 | G159: 8 | H159: 0 | J159: bak 备份表
A160: 159 | B160: bak_20260922_app_check_record_info | C160: C 全连写 | D160: 备份表 | E160: 9 | F160: 0 | G160: 6 | H160: 0 | J160: bak 备份表
A161: 160 | B161: bak_20260922_app_collateral_info | C161: C 全连写 | D161: 备份表 | E161: 20 | F161: 0 | G161: 9 | H161: 0 | J161: bak 备份表
A162: 161 | B162: bak_20260922_app_collateral_mortgage_info | C162: C 全连写 | D162: 备份表 | E162: 14 | F162: 0 | G162: 9 | H162: 0 | J162: bak 备份表
A163: 162 | B163: bak_20260922_app_collateral_restricted_right | C163: C 全连写 | D163: 备份表 | E163: 8 | F163: 0 | G163: 5 | H163: 0 | J163: bak 备份表
A164: 163 | B164: bak_20260922_app_credit_approval_manage_req_info | C164: C 全连写 | D164: 备份表 | E164: 9 | F164: 0 | G164: 6 | H164: 1 | J164: bak 备份表；含大写列，SQL 中须加双引号
A165: 164 | B165: bak_20260922_app_credit_use_info | C165: C 全连写 | D165: 备份表 | E165: 17 | F165: 0 | G165: 13 | H165: 0 | J165: bak 备份表
A166: 165 | B166: bak_20260922_app_customer_info | C166: C 全连写 | D166: 备份表 | E166: 19 | F166: 0 | G166: 16 | H166: 0 | J166: bak 备份表
... A258: 257 | B258: bak_20260922z_app_check_object_info | C258: C 全连写 | D258: 备份表 | E258: 13 | F258: 0 | G258: 10 | H258: 0 | J258: bak 备份表
A259: 258 | B259: index_base_group | C259: C 全连写 | D259: 业务表 | E259: 9 | F259: 0 | G259: 7 | H259: 0
A260: 259 | B260: knowledge_base_group | C260: C 全连写 | D260: 业务表 | E260: 10 | F260: 0 | G260: 8 | H260: 0
A261: 260 | B261: xd_corp_check_checkin | C261: C 全连写 | D261: 业务表 | E261: 11 | F261: 0 | G261: 6 | H261: 0
A262: 261 | B262: xd_corp_check_collateral | C262: C 全连写 | D262: 业务表 | E262: 23 | F262: 0 | G262: 10 | H262: 0
A263: 262 | B263: xd_corp_check_collateral_mortgage | C263: C 全连写 | D263: 业务表 | E263: 14 | F263: 0 | G263: 9 | H263: 0
A264: 263 | B264: xd_corp_check_collateral_restrict | C264: C 全连写 | D264: 业务表 | E264: 9 | F264: 0 | G264: 5 | H264: 0
A265: 264 | B265: xd_corp_check_credit_requirement | C265: C 全连写 | D265: 业务表 | E265: 10 | F265: 0 | G265: 6 | H265: 0
A266: 265 | B266: xd_corp_check_current_opinion | C266: C 全连写 | D266: 业务表 | E266: 13 | F266: 0 | G266: 8 | H266: 0
A267: 266 | B267: xd_corp_check_daily_index | C267: C 全连写 | D267: 业务表 | E267: 11 | F267: 0 | G267: 5 | H267: 0
A268: 267 | B268: xd_corp_check_fixed_loan | C268: C 全连写 | D268: 业务表 | E268: 52 | F268: 0 | G268: 42 | H268: 0
A269: 268 | B269: xd_corp_check_info | C269: C 全连写 | D269: 业务表 | E269: 17 | F269: 0 | G269: 14 | H269: 0
A270: 269 | B270: xd_corp_check_last_opinion | C270: C 全连写 | D270: 业务表 | E270: 13 | F270: 0 | G270: 8 | H270: 0
... A294: 293 | B294: xd_warning_ledger | C294: C 全连写 | D294: 业务表 | E294: 10 | F294: 0 | G294: 6 | H294: 0
